README.md
setup.py
pymovingintelligence/__init__.py
pymovingintelligence/utils.py
pymovingintelligence.egg-info/PKG-INFO
pymovingintelligence.egg-info/SOURCES.txt
pymovingintelligence.egg-info/dependency_links.txt
pymovingintelligence.egg-info/requires.txt
pymovingintelligence.egg-info/top_level.txt