Metadata-Version: 2.1
Name: pymovingintelligence
Version: 0.0.5
Summary: Home Assistant Python 3 API wrapper for MovingIntelligence
Home-page: https://github.com/cyberjunky/python-movingintelligence
Author: Ron Klinkien
Author-email: ron@cyberjunky.nl
License: MIT license
Keywords: asset management,fleet management,api,client
Platform: UNKNOWN
Classifier: Programming Language :: Python :: 3
Classifier: License :: OSI Approved :: MIT License
Classifier: Operating System :: OS Independent
